geojson_validator/__init__.py
geojson_validator/checks_invalid.py
geojson_validator/checks_problematic.py
geojson_validator/fixes.py
geojson_validator/fixes_utils.py
geojson_validator/geometry_utils.py
geojson_validator/geometry_validation.py
geojson_validator/main.py
geojson_validator/schema_validation.py
geojson_validator-0.6.0.dist-info/METADATA
geojson_validator-0.6.0.dist-info/WHEEL
geojson_validator-0.6.0.dist-info/top_level.txt
geojson_validator-0.6.0.dist-info/RECORD
