Metadata-Version: 2.1
Name: geojson-validator
Version: 0.6.0
Summary: Validates and fixes GeoJSON
Author-email: Christoph Rieke <christoph.k.rieke@gmail.com>
License: MIT
Project-URL: Homepage, https://github.com/chrieke/geojson-validator
Project-URL: Changelog, https://github.com/chrieke/geojson-validator/changelog
Keywords: geojson,validation,GIS
Classifier: Programming Language :: Python :: 3
Classifier: License :: OSI Approved :: MIT License
Classifier: Operating System :: OS Independent
Classifier: Development Status :: 4 - Beta
Classifier: Intended Audience :: Developers
Requires-Python: >=3.8
Requires-Dist: loguru>=0.7.2
Requires-Dist: requests>=2.32.3
Requires-Dist: shapely>=2.0.6
